semfio_mist/__init__.py
semfio_mist/config.py
semfio_mist/logger.py
semfio_mist/mist_ap.py
semfio_mist/mist_api.py
semfio_mist/mist_site.py
semfio_mist/mist_wlan.py
semfio_mist-0.1.1.dist-info/LICENSE
semfio_mist-0.1.1.dist-info/METADATA
semfio_mist-0.1.1.dist-info/WHEEL
semfio_mist-0.1.1.dist-info/top_level.txt
semfio_mist-0.1.1.dist-info/RECORD
