Metadata-Version: 2.1
Name: semfio-mist
Version: 0.1.1
Summary: Set of functions to interact with the Mist Juniper Cloud
Home-page: https://github.com/semfionetworks/semfio-mist.git
Author: François Vergès
Author-email: fverges@semfionetworks.com
License: MIT
Platform: UNKNOWN
Classifier: License :: OSI Approved :: MIT License
Classifier: Programming Language :: Python :: 3
Classifier: Programming Language :: Python :: 3.8
Requires-Dist: requests
